arborista/__init__.py
arborista/__main__.py
arborista-0.0.1.dist-info/LICENSE.txt
arborista-0.0.1.dist-info/METADATA
arborista-0.0.1.dist-info/WHEEL
arborista-0.0.1.dist-info/top_level.txt
arborista-0.0.1.dist-info/RECORD
