Metadata-Version: 2.1
Name: arborista
Version: 0.0.1
Summary: An abstract syntax tree transformation tool for bettering Python code.
Home-page: https://github.com/AustinScola/arborista
Author: Austin Scola
Author-email: austinscola@gmail.com
License: UNKNOWN
Platform: UNKNOWN
Classifier: Development Status :: 3 - Alpha
Classifier: Programming Language :: Python :: 3
Classifier: License :: OSI Approved :: MIT License
Classifier: Operating System :: OS Independent
Requires-Python: >=3.6
